docs/source/conf.py
vispipe/__init__.py
vispipe/_gridedit.py
vispipe/_opt_reader.py
vispipe/_options.py
vispipe/_vispipe.py
vispipe/_vispipe.pyi
vispipe/plot_backend.py
vispipe/plot_backend.pyi
vispipe/settings.json
vispipe/vispipe_cli.py
vispipe-1.0.4b1.dist-info/METADATA
vispipe-1.0.4b1.dist-info/WHEEL
vispipe-1.0.4b1.dist-info/entry_points.txt
vispipe-1.0.4b1.dist-info/top_level.txt
vispipe-1.0.4b1.dist-info/RECORD
