Metadata-Version: 2.4
Name: vispipe
Version: 1.0.4b1
Summary: Add your description here
Author-email: Joshua Gramm <joshua.d.gramm@erdc.dren.mil>
Project-URL: Documentation, https://vispipe.readthedocs.io/en/latest/
Project-URL: Repository, https://github.com/julietgolf/vispipe
Requires-Python: >=3.9
Requires-Dist: numpy
Requires-Dist: pint
Requires-Dist: PyMuPDF
Requires-Dist: netCDF4
Requires-Dist: matplotlib
